resnet_simple/__init__.py
resnet_simple/resnet/blocks.py
resnet_simple/resnet/layers.py
resnet_simple/resnet/models.py
resnet_simple/resnet/resnet.py
resnet_simple/resnet/utils.py
resnet_simple-1.0.1.dist-info/LICENSE
resnet_simple-1.0.1.dist-info/METADATA
resnet_simple-1.0.1.dist-info/WHEEL
resnet_simple-1.0.1.dist-info/top_level.txt
resnet_simple-1.0.1.dist-info/RECORD
