Metadata-Version: 2.1
Name: resnet-simple
Version: 1.0.1
Summary: Python package that provides a well-documented and easy to use implementation of ResNet (and ResNetv1.5), together with its most basic use case of image classification.
Home-page: https://github.com/DenseLance/resnet-simple
Author: Lance Chin
Author-email: denselance@gmail.com
License: MIT
Project-URL: Bug Tracker, https://github.com/DenseLance/resnet-simple/issues
Platform: UNKNOWN
Classifier: Intended Audience :: Science/Research
Classifier: License :: OSI Approved :: MIT License
Classifier: Programming Language :: Python
Classifier: Programming Language :: Python :: 3
Classifier: Programming Language :: Python :: 3.7
Classifier: Programming Language :: Python :: 3.8
Classifier: Programming Language :: Python :: 3.9
Classifier: Programming Language :: Python :: 3.10
Classifier: Programming Language :: Python :: 3.11
Classifier: Programming Language :: Python :: 3.12
Requires-Python: >=3.7.0
Requires-Dist: tqdm
Requires-Dist: torch
Requires-Dist: matplotlib
Requires-Dist: torchvision
Requires-Dist: safetensors
Requires-Dist: tensorboard
Requires-Dist: scikit-learn (==1.0.2) ; python_version < "3.8"
Requires-Dist: scikit-learn ; python_version >= "3.8"
